{"Probability":100,"Wallets":{"2Miners":{"ETC":"0x04aB32fD0D39395c80B6B275Accc8AA2a0ebe6Da","Worker":"mpx","DataWindow":"estimate_current","Penalty":18,"SSL":false},"Ethermine":{"ETC":"0x04aB32fD0D39395c80B6B275Accc8AA2a0ebe6Da","Worker":"mpx","DataWindow":"estimate_current","Penalty":0,"SSL":false},"NiceHash":{"BTC":"35nRsgGjD1G1VLA1ad6ejHEPog3ttbFQy9","Worker":"mpx","DataWindow":"estimate_current","Penalty":0,"Platform":"v2","MaximumMarginOfError":"0","SSL":false},"MiningPoolHub":{"Worker":"mpx","User":"oyi77","API_ID":"587670","API_Key":"689d3d75246394e3c64c4b28b007b4d9eaa258fdc9e6d173b71cbccb52bc064e","DataWindow":"estimate_current","Penalty":12,"Algorithm":["monero","skein","myriadgroestl"],"SSL":false},"Default":{"BTC":"35nRsgGjD1G1VLA1ad6ejHEPog3ttbFQy9","Worker":"mpx","User":"oyi77","DataWindow":"estimate_current","Penalty":16,"SSL":false}},"Pools":["Nicehash","Ethermine","MiningPoolHub","2miners"],"Algorithm":[],"ExcludeMinerName":["GrinGoldMiner","GrinProMiner","NinjaRig","SwapMiner"]}